README.rst
setup.cfg
setup.py
pyloger/__init__.py
pyloger/log.py
pyloger.egg-info/PKG-INFO
pyloger.egg-info/SOURCES.txt
pyloger.egg-info/dependency_links.txt
pyloger.egg-info/not-zip-safe
pyloger.egg-info/requires.txt
pyloger.egg-info/top_level.txt