Metadata-Version: 1.1
Name: pyloger
Version: 1.0
Summary: The descusr web application development framework, a syslog project
Home-page: http://www.piadu.com
Author: descusr
Author-email: descusr@163.com
License: BSD-derived (http://www.repoze.org/LICENSE.txt)
Keywords: python syslog,pyloger
Platform: UNKNOWN
Classifier: Intended Audience :: Developers
Classifier: Programming Language :: Python
Classifier: Programming Language :: Python :: 2.6
Classifier: Programming Language :: Python :: 2.7
Classifier: Programming Language :: Python :: 3
Classifier: Programming Language :: Python :: Implementation :: CPython
Classifier: Programming Language :: Python :: Implementation :: PyPy
Classifier: Topic :: Internet :: WWW/HTTP
Classifier: Topic :: Internet :: WWW/HTTP :: WSGI
Classifier: License :: Repoze Public License
